{"type":"FeatureCollection","totalFeatures":5,"features":[{"type":"Feature","id":"ca042022.1","geometry":{"type":"MultiPolygon","coordinates":[[[[121.75255556,24.28776844],[121.75405192,24.28740268],[121.74977975,24.28109332],[121.74900107,24.27940409],[121.74762111,24.27515871],[121.74750479,24.27310479],[121.74617231,24.26804702],[121.74571416,24.267679],[121.74560833,24.26517115],[121.74424197,24.26546451],[121.74482055,24.26860305],[121.74581103,24.27143494],[121.7461537,24.27455793],[121.747471,24.27968511],[121.74839992,24.28166812],[121.75255556,24.28776844]]]]},"geometry_name":"wkb_geometry","properties":{"name":"和平海岸第一棄土區                                                                                                                                                                                                                                                     ","F_area":0.379139321263,"Type":"經濟部工業局                                            "}},{"type":"Feature","id":"ca042022.2","geometry":{"type":"MultiPolygon","coordinates":[[[[121.77151812,24.30639351],[121.77237618,24.30569042],[121.76823841,24.30161925],[121.76741325,24.30223981],[121.77151812,24.30639351]]]]},"geometry_name":"wkb_geometry","properties":{"name":"和平海岸第二棄土區                                                                                                                                                                                                                                                     ","F_area":0.069576629949,"Type":"經濟部工業局                                            "}},{"type":"Feature","id":"ca042022.3","geometry":{"type":"MultiPolygon","coordinates":[[[[121.77380941,24.2991795],[121.77719172,24.29604473],[121.76385908,24.2828184],[121.76032015,24.28591782],[121.77380941,24.2991795]]]]},"geometry_name":"wkb_geometry","properties":{"name":"和平海岸第三棄土區                                                                                                                                                                                                                                                     ","F_area":0.985385358177,"Type":"經濟部工業局                                            "}},{"type":"Feature","id":"ca042022.4","geometry":{"type":"MultiPolygon","coordinates":[[[[120.15149113,23.42455819],[120.14964204,23.42334918],[120.1438301,23.42486419],[120.13988608,23.42503819],[120.13736612,23.42659318],[120.13606613,23.42637217],[120.13603703,23.42657319],[120.13750008,23.42686516],[120.14014513,23.42522915],[120.14398811,23.42514118],[120.14954606,23.4235632],[120.15134007,23.42470717],[120.15149113,23.42455819]]]]},"geometry_name":"wkb_geometry","properties":{"name":"白水湖漁港外航道區域                                                                                                                                                                                                                                                    ","F_area":0.0462074884884,"Type":"嘉義縣政府                                             "}},{"type":"Feature","id":"ca042022.5","geometry":{"type":"MultiPolygon","coordinates":[[[[120.11568001,23.43841005],[120.12484996,23.44078006],[120.1388016,23.44939931],[120.1393635,23.44868366],[120.12181997,23.43742998],[120.12273003,23.42617999],[120.12156998,23.42654006],[120.12093998,23.43720001],[120.11538996,23.43738004],[120.11568001,23.43841005]]]]},"geometry_name":"wkb_geometry","properties":{"name":"東石漁港外航道區域                                                                                                                                                                                                                                                     ","F_area":0.528092201139,"Type":"嘉義縣政府                                             "}}],"crs":{"type":"name","properties":{"name":"urn:ogc:def:crs:EPSG::4326"}}}